scribe/__init__.py
scribe/_version.py
scribe/app.py
scribe/audio.py
scribe/install_desktop.py
scribe/keyboard.py
scribe/models.py
scribe/models.toml
scribe/saverecording.py
scribe/testpynput.py
scribe/util.py
scribe_data/__init__.py
scribe_data/share/icon.png
scribe_data/share/icon_recording.png
scribe_data/share/icon_writing.png
scribe_data/templates/scribe.desktop
scribe_cli-0.13.1.dist-info/LICENSE
scribe_cli-0.13.1.dist-info/METADATA
scribe_cli-0.13.1.dist-info/WHEEL
scribe_cli-0.13.1.dist-info/entry_points.txt
scribe_cli-0.13.1.dist-info/top_level.txt
scribe_cli-0.13.1.dist-info/RECORD
