Metadata-Version: 2.2
Name: scribe-cli
Version: 0.13.1
Summary: scribe is a local speech recognition tool that provides real-time transcription using vosk and whisper AI, with the goal of serving as a virtual keyboard on a computer
Author-email: Mahé Perrette <mahe.perrette@gmail.com>
License: MIT License
Project-URL: Homepage, https://github.com/perrette/scribe
Keywords: speech-to-text,speech recognition,transcription,language,AI,local,API,vosk,whisper,openai,keyboard,clipboard
Classifier: Programming Language :: Python :: 3.9
Classifier: Programming Language :: Python :: 3.10
Classifier: Programming Language :: Python :: 3.11
Classifier: Programming Language :: Python :: 3.12
Classifier: Programming Language :: Python :: 3.13
Classifier: Operating System :: OS Independent
Requires-Python: >=3.9
License-File: LICENSE
Requires-Dist: numpy
Requires-Dist: sounddevice
Requires-Dist: tqdm
Requires-Dist: requests
Requires-Dist: pyperclip
Requires-Dist: unidecode
Requires-Dist: termcolor
Provides-Extra: keyboard
Requires-Dist: pynput; extra == "keyboard"
Provides-Extra: whisper
Requires-Dist: openai-whisper; extra == "whisper"
Provides-Extra: vosk
Requires-Dist: vosk; extra == "vosk"
Provides-Extra: app
Requires-Dist: pystray; extra == "app"
Requires-Dist: PyGObject; extra == "app"
Provides-Extra: openai
Requires-Dist: openai; extra == "openai"
Requires-Dist: soundfile; extra == "openai"
Provides-Extra: all
Requires-Dist: pynput; extra == "all"
Requires-Dist: openai-whisper; extra == "all"
Requires-Dist: openai; extra == "all"
Requires-Dist: soundfile; extra == "all"
Requires-Dist: vosk; extra == "all"
Requires-Dist: pystray; extra == "all"
